skhubness/__init__.py
skhubness/__pycache__/__init__.cpython-37.pyc
skhubness/analysis/__init__.py
skhubness/analysis/estimation.py
skhubness/analysis/__pycache__/__init__.cpython-37.pyc
skhubness/analysis/__pycache__/estimation.cpython-37.pyc
skhubness/analysis/tests/__init__.py
skhubness/analysis/tests/test_estimation.py
skhubness/analysis/tests/__pycache__/__init__.cpython-37.pyc
skhubness/analysis/tests/__pycache__/test_dummy.cpython-37-pytest-5.0.1.pyc
skhubness/analysis/tests/__pycache__/test_estimation.cpython-37-pytest-5.0.1.pyc
skhubness/analysis/tests/__pycache__/test_estimation.cpython-37-pytest-5.2.1.pyc
skhubness/analysis/tests/__pycache__/test_estimation.cpython-37.pyc
skhubness/data/__init__.py
skhubness/data/load_dataset.py
skhubness/data/__pycache__/__init__.cpython-37.pyc
skhubness/data/__pycache__/load_dataset.cpython-37.pyc
skhubness/data/dexter/ABOUT
skhubness/data/dexter/dexter_train.data
skhubness/data/dexter/dexter_train.labels
skhubness/data/tests/__init__.py
skhubness/data/tests/test_load_datasets.py
skhubness/data/tests/__pycache__/__init__.cpython-37.pyc
skhubness/data/tests/__pycache__/test_load_datasets.cpython-37-PYTEST.pyc
skhubness/data/tests/__pycache__/test_load_datasets.cpython-37-pytest-5.0.1.pyc
skhubness/data/tests/__pycache__/test_load_datasets.cpython-37-pytest-5.2.1.pyc
skhubness/data/tests/__pycache__/test_load_datasets.cpython-37.pyc
skhubness/neighbors/__init__.py
skhubness/neighbors/approximate_neighbors.py
skhubness/neighbors/ball_tree.py
skhubness/neighbors/base.py
skhubness/neighbors/classification.py
skhubness/neighbors/dist_metrics.py
skhubness/neighbors/graph.py
skhubness/neighbors/hnsw.py
skhubness/neighbors/kd_tree.py
skhubness/neighbors/kde.py
skhubness/neighbors/lof.py
skhubness/neighbors/lsh.py
skhubness/neighbors/nca.py
skhubness/neighbors/nearest_centroid.py
skhubness/neighbors/nng.py
skhubness/neighbors/onng.py
skhubness/neighbors/quad_tree.py
skhubness/neighbors/random_projection_trees.py
scikit_hubness-0.21.1.dist-info/LICENSE.txt
scikit_hubness-0.21.1.dist-info/METADATA
scikit_hubness-0.21.1.dist-info/WHEEL
scikit_hubness-0.21.1.dist-info/top_level.txt
scikit_hubness-0.21.1.dist-info/RECORD
