Metadata-Version: 2.1
Name: scikit-hubness
Version: 0.21.1
Summary: Hubness reduction and analysis tools
Home-page: https://github.com/VarIr/scikit-hubness
Author: Roman Feldbauer
Author-email: roman.feldbauer@univie.ac.at
Maintainer: Roman Feldbauer
Maintainer-email: roman.feldbauer@univie.ac.at
License: UNKNOWN
Project-URL: Bug Reports, https://github.com/VarIr/scikit-hubness/issues
Project-URL: Documentation, https://scikit-hubness.readthedocs.io
Project-URL: Say Thanks!, https://saythanks.io/to/VarIr
Project-URL: Source, https://github.com/VarIr/scikit-hubness/
Keywords: machine-learning high-dimensional-data hubness nearest-neighbor data-science data-mining artificial-intelligence
Platform: UNKNOWN
Classifier: Development Status :: 4 - Beta
Classifier: Environment :: Console
Classifier: Intended Audience :: Science/Research
Classifier: License :: OSI Approved :: BSD License
Classifier: Operating System :: POSIX :: Linux
Classifier: Operating System :: MacOS :: MacOS X
Classifier: Operating System :: Microsoft :: Windows
Classifier: Programming Language :: Python :: 3
Classifier: Programming Language :: Python :: 3.7
Classifier: Programming Language :: Python :: 3.8
Classifier: Topic :: Scientific/Engineering
Classifier: Topic :: Scientific/Engineering :: Artificial Intelligence
Requires-Python: >=3.7
Provides-Extra: test
